scramble_history/__init__.py
scramble_history/__main__.py
scramble_history/average_parser.py
scramble_history/config.py
scramble_history/cstimer.py
scramble_history/cstimer_scramble_type.py
scramble_history/error.py
scramble_history/group_operations.py
scramble_history/invert_scramble.py
scramble_history/log.py
scramble_history/models.py
scramble_history/py.typed
scramble_history/query.py
scramble_history/source_merger.py
scramble_history/timeformat.py
scramble_history/twistytimer.py
scramble_history/wca_export.py
scramble_history-0.1.15.dist-info/LICENSE
scramble_history-0.1.15.dist-info/METADATA
scramble_history-0.1.15.dist-info/WHEEL
scramble_history-0.1.15.dist-info/entry_points.txt
scramble_history-0.1.15.dist-info/top_level.txt
scramble_history-0.1.15.dist-info/RECORD
