Metadata-Version: 2.1
Name: scramble-history
Version: 0.1.15
Summary: parses scramble history from cstimer.net and other sources
Home-page: https://github.com/seanbreckenridge/scramble-history
Author: Sean Breckenridge
Author-email: seanbrecke@gmail.com
License: MIT
Keywords: cubing data
Classifier: License :: OSI Approved :: MIT License
Classifier: Programming Language :: Python
Classifier: Programming Language :: Python :: 3
Classifier: Programming Language :: Python :: 3.8
Classifier: Programming Language :: Python :: 3.9
Classifier: Programming Language :: Python :: 3.10
Requires-Python: >=3.8
License-File: LICENSE
Requires-Dist: click (>=8.0)
Requires-Dist: requests
Requires-Dist: logzero
Requires-Dist: IPython
Requires-Dist: platformdirs
Requires-Dist: pytimeparse
Requires-Dist: autotui (>=0.4.3)
Requires-Dist: more-itertools
Requires-Dist: pyyaml
Requires-Dist: tabulate
Requires-Dist: simplejson
Provides-Extra: optional
Requires-Dist: orjson ; extra == 'optional'
Requires-Dist: seaborn ; extra == 'optional'
Provides-Extra: testing
Requires-Dist: pytest ; extra == 'testing'
Requires-Dist: mypy ; extra == 'testing'
Requires-Dist: flake8 ; extra == 'testing'
